setup.py
bin/kegboard_daemon.py
bin/kegbot_core.py
bin/lcd_daemon.py
bin/rfid_daemon.py
bin/test_flow.py
kegbot/__init__.py
kegbot/pycore/__init__.py
kegbot/pycore/backend.py
kegbot/pycore/common_defs.py
kegbot/pycore/flow.py
kegbot/pycore/flow_meter.py
kegbot/pycore/flow_meter_test.py
kegbot/pycore/flow_test.py
kegbot/pycore/kb_threads.py
kegbot/pycore/kbevent.py
kegbot/pycore/kegbot_app.py
kegbot/pycore/kegbot_test.py
kegbot/pycore/kegnet.py
kegbot/pycore/manager.py
kegbot/pycore/manager_test.py
kegbot/pycore/tap.py
kegbot/pycore/tap_test.py
kegbot_pycore.egg-info/PKG-INFO
kegbot_pycore.egg-info/SOURCES.txt
kegbot_pycore.egg-info/dependency_links.txt
kegbot_pycore.egg-info/namespace_packages.txt
kegbot_pycore.egg-info/requires.txt
kegbot_pycore.egg-info/top_level.txt