Metadata-Version: 1.0
Name: kegbot-pycore
Version: 1.2.1
Summary: Standalone Python Kegbot Core.
Home-page: https://kegbot.org/docs/pycore
Author: Bevbot LLC
Author-email: info@bevbot.com
License: UNKNOWN
Platform: UNKNOWN
